{"FowKZYKQVSJcVjzmbAfN3A==":"53524786_2364265040259610_5289766379853971456_n-121x121.jpg","OHKIUKOG8L78YwGPatk5MQ==":"download-301x167.jpg","B9etY8agaQrW196P8yQ2zA==":"53524786_2364265040259610_5289766379853971456_n-121x121.jpeg","8AixVeI9ih19ppLBK42K4Q==":"53524786_2364265040259610_5289766379853971456_n-1052x1052.jpg","YWrDZSq90jukU7D0oq5AoQ==":"53524786_2364265040259610_5289766379853971456_n-1052x1052.jpeg","CCZlm1+KUB6/fDC27LZV5Q==":"53524786_2364265040259610_5289766379853971456_n-1-1052x1052.jpeg","Blxuh8aZLGur3IQmM1TDxw==":"chris-ried-ieic5tq8ymk-unsplas_1200x768.webp","y/hn9SUZEVUno2qf7kmteg==":"chris-ried-ieic5tq8ymk-unsplas_1200x768-1.webp","E6jZ5pch8ITSrbrY5TwUkg==":"avatars-000226490433-1z9tzp-t500x500-500x500.jpg","e4dGTzRGM3rPJoRr8NDc8A==":"album_art-838x816.jpg","FaP/iSYjCf4gWHsp9g744w==":"skew3-838x838.jpg","wSfaIjH7L1geyUpTFnBZIg==":"untitled_480x480-480x480.png","WychqGTAwGDcZzV2PH9SBQ==":"sri%20rama%20namam_aa-838x838.jpg","XUTUqIGwcqZEGrM3wMjzBg==":"circulation-696x333.png","fIJe7orHRzw+PkSDTO5+iw==":"chann-1076x807.jpg","7xGD7zJkGwI9SVWSauyQTw==":"bend%20apex_u-1108x541.png","XHJytEUecIqZ6kAxW40O6Q==":"bend%20apex_v-1108x540.png","6l3uIuo6x0QhUoemIFEB3Q==":"k_norm_14.5cm_interface-1108x833.png","Or88k6fWdYBmQo3YjgIcBQ==":"mape.tif","vKxUu7ewWcTifOhTRi2ifw==":"intaerface_co_20.5l_ff_cuml-1108x554.png","lKbGTsIgvBtSMtaqg/roJw==":"intaerface_co_20.5l_ff_cuml-1-1108x554.png","Cau1uKx0LAXkZCPL9WW7Yg==":"k_norm_14.5cm_interface-1-1108x833.png","bLhxXsrtzzH1xsO6UMyq8w==":"bend%20apex_u-1108x541.png","OFxOZYCsNb3bHRSRVl0vsA==":"bend%20apex_v-1108x540.png","PnyEZkXYRdQKy4w0wh6ixw==":"picture1-427x215.jpg","aOXBarZ92xFtYXtaOuQN2Q==":"picture2-819x461.jpg","Q1IpKiL2Fuox35Qazvi4PQ==":"picture4-421x215.jpg","LaiqtutXMinb6N3OgYyrAQ==":"picture6-324x226.jpg","w8D1IIgRCYD8MfBgfaR7rg==":"picture3-167x292.jpg","t1oTLCDr93JMA+heXF+qNQ==":"picture5-421x254.jpg","bRx9P+azu9crJTF1i7cWoA==":"picture7-886x577.png","LSMwrxdpSUMS5M0DUlfLmQ==":"picture8-886x652.png","/Qz2/tNmo2KR/PUBhPhQgQ==":"picture2-819x461.jpeg","WZAmRI3jSXhC9j19L19dbA==":"picture1-427x215.jpeg","xk3m53D5P2c/0kWTrWyOMQ==":"picture3-167x292.jpeg","JHq5zjyK+vvJYzvI9QhjcA==":"picture5-421x254.jpeg","tPjs/NetXeMJjjG9f1q8Vg==":"picture7-1-886x577.png","qb715x1sGMV2XJAQIdTfUA==":"6y2pz-1680x1050.jpg","aI/6+RSx3eK15tu1Yzd+Yw==":"6y2pz-1680x1050.jpeg","TYl+pA1vxUtTSVuv+E0B1g==":"6y2pz-1-1680x1050.jpeg","Qb3bVHS+GmuRcR7l2f2DiA==":"aaupdate-646x646.png"}